ping/__init__.py
ping/ping.py
alphabet5_ping-0.0.8.dist-info/LICENSE.md
alphabet5_ping-0.0.8.dist-info/METADATA
alphabet5_ping-0.0.8.dist-info/WHEEL
alphabet5_ping-0.0.8.dist-info/entry_points.txt
alphabet5_ping-0.0.8.dist-info/top_level.txt
alphabet5_ping-0.0.8.dist-info/RECORD
